clikan.py
clikan-0.4.4.dist-info/METADATA
clikan-0.4.4.dist-info/WHEEL
clikan-0.4.4.dist-info/entry_points.txt
clikan-0.4.4.dist-info/top_level.txt
clikan-0.4.4.dist-info/RECORD
