Metadata-Version: 2.1
Name: clikan
Version: 0.4.4
Summary: Simple CLI-based Kanban board
Home-page: https://github.com/kitplummer/clikan
Author: Kit Plummer
Author-email: kitplummer@gmail.com
Classifier: License :: OSI Approved :: MIT License
Classifier: Programming Language :: Python :: 2.7
Classifier: Programming Language :: Python :: 3
Classifier: Environment :: Console
Requires-Dist: Click
Requires-Dist: click-default-group
Requires-Dist: pyyaml
Requires-Dist: rich
